__init__.py
config.py
constants.py
exporter.py
logger.py
plc_reader.py
plc_exporter-0.1.1.dist-info/licenses/LICENSE.txt
plc_exporter-0.1.1.dist-info/METADATA
plc_exporter-0.1.1.dist-info/WHEEL
plc_exporter-0.1.1.dist-info/entry_points.txt
plc_exporter-0.1.1.dist-info/top_level.txt
plc_exporter-0.1.1.dist-info/RECORD
