Metadata-Version: 2.4
Name: plc-exporter
Version: 0.1.1
Summary: Metrics exporter for PLC
Author: sourcehawk
Maintainer: sourcehawk
Project-URL: Homepage, https://github.com/sourcehawk/plc-exporter
Project-URL: Source, https://github.com/sourcehawk/plc-exporter
Keywords: plc,modbus,tcp,metrics,exporter,prometheus
Classifier: Development Status :: 3 - Alpha
Classifier: Intended Audience :: Developers
Classifier: Topic :: Software Development :: Build Tools
Classifier: License :: OSI Approved :: MIT License
Classifier: Programming Language :: Python :: 3
Classifier: Programming Language :: Python :: 3.8
Classifier: Programming Language :: Python :: 3.9
Classifier: Programming Language :: Python :: 3.10
Classifier: Programming Language :: Python :: 3.11
Classifier: Programming Language :: Python :: 3.12
Classifier: Programming Language :: Python :: 3 :: Only
Requires-Python: >=3.8
License-File: LICENSE.txt
Requires-Dist: prometheus_client==0.21.0
Requires-Dist: pymodbus==3.7.2
Requires-Dist: asyncio==3.4.3
Requires-Dist: PyYAML==6.0.2
Requires-Dist: humanfriendly==10.0
Requires-Dist: schema==0.7.7
Provides-Extra: dev
Requires-Dist: check-manifest; extra == "dev"
Provides-Extra: test
Requires-Dist: coverage; extra == "test"
Dynamic: license-file
